google/cloud/dataflow/__init__.py
google/cloud/dataflow/gapic_version.py
google/cloud/dataflow/py.typed
google/cloud/dataflow_v1beta3/__init__.py
google/cloud/dataflow_v1beta3/gapic_metadata.json
google/cloud/dataflow_v1beta3/gapic_version.py
google/cloud/dataflow_v1beta3/py.typed
google/cloud/dataflow_v1beta3/services/__init__.py
google/cloud/dataflow_v1beta3/services/flex_templates_service/__init__.py
google/cloud/dataflow_v1beta3/services/flex_templates_service/async_client.py
google/cloud/dataflow_v1beta3/services/flex_templates_service/client.py
google/cloud/dataflow_v1beta3/services/flex_templates_service/transports/__init__.py
google/cloud/dataflow_v1beta3/services/flex_templates_service/transports/base.py
google/cloud/dataflow_v1beta3/services/flex_templates_service/transports/grpc.py
google/cloud/dataflow_v1beta3/services/flex_templates_service/transports/grpc_asyncio.py
google/cloud/dataflow_v1beta3/services/flex_templates_service/transports/rest.py
google/cloud/dataflow_v1beta3/services/flex_templates_service/transports/rest_base.py
google/cloud/dataflow_v1beta3/services/jobs_v1_beta3/__init__.py
google/cloud/dataflow_v1beta3/services/jobs_v1_beta3/async_client.py
google/cloud/dataflow_v1beta3/services/jobs_v1_beta3/client.py
google/cloud/dataflow_v1beta3/services/jobs_v1_beta3/pagers.py
google/cloud/dataflow_v1beta3/services/jobs_v1_beta3/transports/__init__.py
google/cloud/dataflow_v1beta3/services/jobs_v1_beta3/transports/base.py
google/cloud/dataflow_v1beta3/services/jobs_v1_beta3/transports/grpc.py
google/cloud/dataflow_v1beta3/services/jobs_v1_beta3/transports/grpc_asyncio.py
google/cloud/dataflow_v1beta3/services/jobs_v1_beta3/transports/rest.py
google/cloud/dataflow_v1beta3/services/jobs_v1_beta3/transports/rest_base.py
google/cloud/dataflow_v1beta3/services/messages_v1_beta3/__init__.py
google/cloud/dataflow_v1beta3/services/messages_v1_beta3/async_client.py
google/cloud/dataflow_v1beta3/services/messages_v1_beta3/client.py
google_cloud_dataflow_client-0.9.0.dist-info/LICENSE
google_cloud_dataflow_client-0.9.0.dist-info/METADATA
google_cloud_dataflow_client-0.9.0.dist-info/WHEEL
google_cloud_dataflow_client-0.9.0.dist-info/top_level.txt
google_cloud_dataflow_client-0.9.0.dist-info/RECORD
